pytest_rerunfailures.py
pytest_rerunfailures-16.0.dist-info/licenses/LICENSE
pytest_rerunfailures-16.0.dist-info/METADATA
pytest_rerunfailures-16.0.dist-info/WHEEL
pytest_rerunfailures-16.0.dist-info/entry_points.txt
pytest_rerunfailures-16.0.dist-info/top_level.txt
pytest_rerunfailures-16.0.dist-info/RECORD
