Metadata-Version: 2.4
Name: pytest-rerunfailures
Version: 16.0
Summary: pytest plugin to re-run tests to eliminate flaky failures
Author-email: Leah Klearman <lklrmn@gmail.com>
License: MPL-2.0
Project-URL: Homepage, https://github.com/pytest-dev/pytest-rerunfailures
Keywords: failures,flaky,pytest,rerun
Classifier: Development Status :: 5 - Production/Stable
Classifier: Framework :: Pytest
Classifier: Intended Audience :: Developers
Classifier: Operating System :: MacOS :: MacOS X
Classifier: Operating System :: Microsoft :: Windows
Classifier: Operating System :: POSIX
Classifier: Programming Language :: Python :: 3 :: Only
Classifier: Programming Language :: Python :: 3.9
Classifier: Programming Language :: Python :: 3.10
Classifier: Programming Language :: Python :: 3.11
Classifier: Programming Language :: Python :: 3.12
Classifier: Programming Language :: Python :: 3.13
Classifier: Programming Language :: Python :: 3.14
Classifier: Programming Language :: Python :: Implementation :: CPython
Classifier: Programming Language :: Python :: Implementation :: PyPy
Classifier: Topic :: Software Development :: Quality Assurance
Classifier: Topic :: Software Development :: Testing
Classifier: Topic :: Utilities
Requires-Python: >=3.9
License-File: LICENSE
Requires-Dist: packaging>=17.1
Requires-Dist: pytest!=8.2.2,>=7.4
Dynamic: license-file
